generate_python.py
main.py
schemantis_cli-0.0.10.dist-info/METADATA
schemantis_cli-0.0.10.dist-info/WHEEL
schemantis_cli-0.0.10.dist-info/entry_points.txt
schemantis_cli-0.0.10.dist-info/top_level.txt
schemantis_cli-0.0.10.dist-info/RECORD
