Metadata-Version: 2.1
Name: schemantis-cli
Version: 0.0.10
Summary: A python comand line tool that integrates with schemantis
Author-email: James Rao <james@10xtech.ca>
Project-URL: Homepage, https://git.10xtech.ca/root/schemantis-cli
Project-URL: Bug Tracker, https://git.10xtech.ca/root/schemantis-cli
Classifier: Programming Language :: Python :: 3
Classifier: License :: OSI Approved :: MIT License
Classifier: Operating System :: OS Independent
Requires-Python: >=3.7
Requires-Dist: schemantis
